fit2parquets/__init__.py
fit2parquets/parser.py
fit2parquets/utils/__init__.py
fit2parquets/utils/config.py
fit2parquets/utils/logger.py
fit2parquets-0.7.0.dist-info/LICENSE
fit2parquets-0.7.0.dist-info/METADATA
fit2parquets-0.7.0.dist-info/WHEEL
fit2parquets-0.7.0.dist-info/entry_points.txt
fit2parquets-0.7.0.dist-info/RECORD
