Metadata-Version: 2.1
Name: fit2parquets
Version: 0.7.0
Summary: 
Home-page: https://github.com/thomascamminady/fit2parquets
Author: Thomas Camminady
Author-email: 0milieux_member@icloud.com
Requires-Python: >=3.10,<3.13
Classifier: Programming Language :: Python :: 3
Classifier: Programming Language :: Python :: 3.10
Classifier: Programming Language :: Python :: 3.11
Classifier: Programming Language :: Python :: 3.12
Requires-Dist: fire (>=0.7.0,<0.8.0)
Requires-Dist: garmin-fit-sdk (>=21.141.0,<22.0.0)
Requires-Dist: polars (>=1.9.0,<2.0.0)
Requires-Dist: rich (>=13.9.4,<14.0.0)
Project-URL: Documentation, https://thomascamminady.github.io/fit2parquets
Project-URL: Repository, https://github.com/thomascamminady/fit2parquets
